ParsWeather/ParsWeather.py
ParsWeather/__init__.py
parsweather-1.1.3.dist-info/licenses/LICENSE
parsweather-1.1.3.dist-info/METADATA
parsweather-1.1.3.dist-info/WHEEL
parsweather-1.1.3.dist-info/top_level.txt
parsweather-1.1.3.dist-info/RECORD
