Metadata-Version: 2.4
Name: ParsWeather
Version: 1.1.3
Summary: A Python package for getting Iran's weather data, including temperature and RealFeel.
Author-email: Ali Ayati Qaffari <ayatiali910@gmail.com>
License-Expression: MIT
Project-URL: Profile, https://github.com/MrAAQPy
Project-URL: github, https://github.com/MrAAQPy/ParsWeather
Project-URL: issue, https://github.com/MrAAQPy/ParsWeather/issues
Project-URL: bale, https://ble.ir/aaq1386
Requires-Python: >=3.7
License-File: LICENSE
Requires-Dist: beautifulsoup4
Requires-Dist: lxml
Requires-Dist: requests
Dynamic: license-file
